[
  {
    "ContainingType": "User_Managment.Controllers.UserController",
    "Method": "DeleteUser",
    "RelativePath": "Api/{userId}",
    "HttpMethod": "DELETE",
    "IsController": true,
    "Order": 0,
    "Parameters": [
      {
        "Name": "userId",
        "Type": "System.Int32",
        "IsRequired": true
      }
    ],
    "ReturnTypes": []
  },
  {
    "ContainingType": "User_Managment.Controllers.UserController",
    "Method": "AssignRoleToUser",
    "RelativePath": "Api/Assign-Role",
    "HttpMethod": "POST",
    "IsController": true,
    "Order": 0,
    "Parameters": [
      {
        "Name": "UserName",
        "Type": "System.String",
        "IsRequired": false
      },
      {
        "Name": "RoleID",
        "Type": "System.Int32",
        "IsRequired": false
      }
    ],
    "ReturnTypes": []
  },
  {
    "ContainingType": "User_Managment.Controllers.UserController",
    "Method": "GetAllUsers",
    "RelativePath": "Api/GetAllUser",
    "HttpMethod": "GET",
    "IsController": true,
    "Order": 0,
    "Parameters": [],
    "ReturnTypes": []
  },
  {
    "ContainingType": "User_Managment.Controllers.UserController",
    "Method": "Login",
    "RelativePath": "Api/Login",
    "HttpMethod": "POST",
    "IsController": true,
    "Order": 0,
    "Parameters": [
      {
        "Name": "request",
        "Type": "User_Managment.Controllers.LoginAndRegisterRequest",
        "IsRequired": true
      }
    ],
    "ReturnTypes": []
  },
  {
    "ContainingType": "User_Managment.Controllers.UserController",
    "Method": "Register",
    "RelativePath": "Api/Register",
    "HttpMethod": "POST",
    "IsController": true,
    "Order": 0,
    "Parameters": [
      {
        "Name": "request",
        "Type": "User_Managment.Controllers.LoginAndRegisterRequest",
        "IsRequired": true
      }
    ],
    "ReturnTypes": []
  },
  {
    "ContainingType": "User_Managment.Controllers.UserController",
    "Method": "UpdateUser",
    "RelativePath": "Api/UpdateUser/{id}",
    "HttpMethod": "PUT",
    "IsController": true,
    "Order": 0,
    "Parameters": [
      {
        "Name": "id",
        "Type": "System.Int32",
        "IsRequired": true
      },
      {
        "Name": "request",
        "Type": "User_Managment.Controllers.LoginAndRegisterRequest",
        "IsRequired": true
      }
    ],
    "ReturnTypes": []
  },
  {
    "ContainingType": "User_Managment.Controllers.UserController",
    "Method": "GetUser",
    "RelativePath": "Api/User/{id}",
    "HttpMethod": "GET",
    "IsController": true,
    "Order": 0,
    "Parameters": [
      {
        "Name": "id",
        "Type": "System.Int32",
        "IsRequired": true
      }
    ],
    "ReturnTypes": []
  }
]